AUTHORS
MANIFEST.in
setup.py
django_webmaster.egg-info/PKG-INFO
django_webmaster.egg-info/SOURCES.txt
django_webmaster.egg-info/dependency_links.txt
django_webmaster.egg-info/not-zip-safe
django_webmaster.egg-info/top_level.txt
webmaster/__init__.py
webmaster/admin.py
webmaster/models.py