Metadata-Version: 1.1
Name: django-webmaster
Version: 0.0.2
Summary: A very basic tool to keep track of your domain names and servers.
Home-page: https://github.com/joncombe/django-webmaster
Author: Jon Combe
Author-email: pypi@joncombe.net
License: BSD licence, see LICENCE file
Platform: UNKNOWN
Classifier: Development Status :: 3 - Alpha
Classifier: Environment :: Web Environment
Classifier: Framework :: Django
Classifier: Intended Audience :: Developers
Classifier: Intended Audience :: System Administrators
Classifier: License :: OSI Approved :: BSD License
Classifier: Natural Language :: English
Classifier: Programming Language :: Python
Classifier: Topic :: System :: Systems Administration
